{
  "version": "7",
  "dialect": "postgresql",
  "entries": [
    {
      "idx": 0,
      "version": "7",
      "when": 1745518076143,
      "tag": "0000_init-db",
      "breakpoints": true
    },
    {
      "idx": 1,
      "version": "7",
      "when": 1778954027871,
      "tag": "0001_last_the_call",
      "breakpoints": true
    },
    {
      "idx": 2,
      "version": "7",
      "when": 1779493892986,
      "tag": "0002_volatile_silver_sable",
      "breakpoints": true
    },
    {
      "idx": 3,
      "version": "7",
      "when": 1779778682754,
      "tag": "0003_dazzling_hitman",
      "breakpoints": true
    },
    {
      "idx": 4,
      "version": "7",
      "when": 1779783864076,
      "tag": "0004_omniscient_may_parker",
      "breakpoints": true
    },
    {
      "idx": 5,
      "version": "7",
      "when": 1779814690974,
      "tag": "0005_clumsy_ser_duncan",
      "breakpoints": true
    },
    {
      "idx": 6,
      "version": "7",
      "when": 1779890410068,
      "tag": "0006_simple_veda",
      "breakpoints": true
    },
    {
      "idx": 7,
      "version": "7",
      "when": 1779971873533,
      "tag": "0007_unified_schema",
      "breakpoints": true
    },
    {
      "idx": 8,
      "version": "7",
      "when": 1780000000000,
      "tag": "0008_jobs",
      "breakpoints": true
    }
  ]
}